cnat/__init__.py
cnat/__main__.py
cnat/api.py
cnat/cli.py
cnat/utils.py
cnat/translators/__init__.py
cnat/translators/shona.py
cnat-0.1.0.dist-info/licenses/LICENSE
cnat-0.1.0.dist-info/METADATA
cnat-0.1.0.dist-info/WHEEL
cnat-0.1.0.dist-info/entry_points.txt
cnat-0.1.0.dist-info/top_level.txt
cnat-0.1.0.dist-info/RECORD
