Metadata-Version: 2.4
Name: cnat
Version: 0.1.0
Summary: Write code in your native language. Cnat translates it into standard code.
Author-email: "Caleb M. Sibanda" <darkian.dev@gmail.com>
License: MIT
Project-URL: Homepage, https://github.com/2kDarki/cnat
Project-URL: Documentation, https://github.com/2kDarki/cnat#readme
Project-URL: Repository, https://github.com/2kDarki/cnat
Project-URL: Issues, https://github.com/2kDarki/cnat/issues
Keywords: translator,native language,code,i18n,shona,localization
Classifier: Programming Language :: Python :: 3
Classifier: License :: OSI Approved :: MIT License
Classifier: Operating System :: OS Independent
Classifier: Topic :: Software Development :: Compilers
Classifier: Intended Audience :: Developers
Requires-Python: >=3.10
License-File: LICENSE
Dynamic: license-file
